cloai/__init__.py
cloai/exceptions.py
cloai/logs.py
cloai/llm/__init__.py
cloai/llm/bedrock.py
cloai/llm/llm.py
cloai/llm/ollama.py
cloai/llm/openai.py
cloai/llm/prompts.py
cloai/llm/utils.py
cloai-1.1.0.dist-info/METADATA
cloai-1.1.0.dist-info/WHEEL
cloai-1.1.0.dist-info/licenses/LICENSE
cloai-1.1.0.dist-info/RECORD
