Metadata-Version: 2.4
Name: cloai
Version: 1.1.0
Summary: A generic interface for AI models.
License-File: LICENSE
Requires-Python: >3.10
Requires-Dist: anthropic[bedrock]>=0.37.1
Requires-Dist: httpx==0.27
Requires-Dist: instructor[anthropic]>1.6
Requires-Dist: ollama>=0.4.5
Requires-Dist: openai>=1.58.1
